imghdr/__init__.py
imghdr/py.typed
imghdr_lts-1.0.0.dist-info/LICENCE
imghdr_lts-1.0.0.dist-info/METADATA
imghdr_lts-1.0.0.dist-info/WHEEL
imghdr_lts-1.0.0.dist-info/top_level.txt
imghdr_lts-1.0.0.dist-info/RECORD
